odoo/addons/currency_rate_update_ee_beep/README.rst
odoo/addons/currency_rate_update_ee_beep/__init__.py
odoo/addons/currency_rate_update_ee_beep/__manifest__.py
odoo/addons/currency_rate_update_ee_beep/i18n/currency_rate_update_ee_beep.pot
odoo/addons/currency_rate_update_ee_beep/readme/CONFIGURE.rst
odoo/addons/currency_rate_update_ee_beep/readme/CONTRIBUTORS.rst
odoo/addons/currency_rate_update_ee_beep/readme/CREDITS.rst
odoo/addons/currency_rate_update_ee_beep/readme/DESCRIPTION.rst
odoo/addons/currency_rate_update_ee_beep/readme/INSTALL.rst
odoo/addons/currency_rate_update_ee_beep/services/__init__.py
odoo/addons/currency_rate_update_ee_beep/services/update_service_ee_beep.py
odoo/addons/currency_rate_update_ee_beep/static/description/icon.png
odoo/addons/currency_rate_update_ee_beep/static/description/index.html
odoo11_addon_currency_rate_update_ee_beep-11.0.1.0.0.99.dev4.dist-info/METADATA
odoo11_addon_currency_rate_update_ee_beep-11.0.1.0.0.99.dev4.dist-info/WHEEL
odoo11_addon_currency_rate_update_ee_beep-11.0.1.0.0.99.dev4.dist-info/top_level.txt
odoo11_addon_currency_rate_update_ee_beep-11.0.1.0.0.99.dev4.dist-info/RECORD
